django_model_info/__init__.py
django_model_info/admin.py
django_model_info/apps.py
django_model_info/models.py
django_model_info/urls.py
django_model_info/management/__init__.py
django_model_info/management/commands/__init__.py
django_model_info/management/commands/migrationgraph.py
django_model_info/management/commands/modelfilters.py
django_model_info/management/commands/modelgraph.py
django_model_info/management/commands/modelinfo.py
django_model_info/management/commands/common_utils/__init__.py
django_model_info/management/commands/common_utils/_cache.py
django_model_info/management/commands/common_utils/_settings.py
django_model_info/management/commands/modelfilters_utils/__init__.py
django_model_info/management/commands/modelfilters_utils/_field_utils.py
django_model_info/management/commands/modelgraph_utils/__init__.py
django_model_info/management/commands/modelgraph_utils/_analysis.py
django_model_info/management/commands/modelgraph_utils/_base.py
django_model_info/management/commands/modelgraph_utils/_dot.py
django_model_info/management/commands/modelgraph_utils/_graph.py
django_model_info/management/commands/modelgraph_utils/_mermaidjs.py
django_model_info/management/commands/modelinfo_utils/__init__.py
django_model_info/management/commands/modelinfo_utils/_common_utils.py
django_model_info/management/commands/modelinfo_utils/_field_attr_utils.py
django_model_info/management/commands/modelinfo_utils/_info_classes.py
django_model_info/management/commands/modelinfo_utils/_manager_utils.py
django_model_info/management/commands/modelinfo_utils/_markdown_utils.py
django_model_info/management/commands/modelinfo_utils/_method_attr_utils.py
django_model_info/management/commands/modelinfo_utils/_model_attr_utils.py
django_model_info-2024.11.5.dist-info/AUTHORS.md
django_model_info-2024.11.5.dist-info/LICENSE
django_model_info-2024.11.5.dist-info/METADATA
django_model_info-2024.11.5.dist-info/WHEEL
django_model_info-2024.11.5.dist-info/top_level.txt
django_model_info-2024.11.5.dist-info/RECORD
