Metadata-Version: 2.1
Name: django-model-info
Version: 2024.11.5
Summary: A set of Django Management Commands to help you understand and visualize your project's models.
Author-email: Jack Linke <jacklinke@gmail.com>
License: MIT
Project-URL: Homepage, https://github.com/OmenApps/django-model-info
Project-URL: Repository, https://github.com/OmenApps/django-model-info
Project-URL: Documentation, https://django-model-info.readthedocs.io/en/latest/
Project-URL: Changelog, https://github.com/OmenApps/django-model-info/blob/main/CHANGELOG.md
Classifier: Framework :: Django
Classifier: Programming Language :: Python :: 3
Classifier: Intended Audience :: Developers
Classifier: License :: OSI Approved :: MIT License
Classifier: Operating System :: OS Independent
Classifier: Topic :: Documentation
Classifier: Topic :: Utilities
Requires-Python: <4.0,>=3.10
License-File: LICENSE
License-File: AUTHORS.md
Requires-Dist: django
Requires-Dist: networkx>=3.4.2
Requires-Dist: pydot>=3.0.2
Requires-Dist: rich>=13
Provides-Extra: dev
Requires-Dist: invoke>=2; extra == "dev"
Requires-Dist: twine>=4; extra == "dev"
Requires-Dist: wheel>=0.38.1; extra == "dev"
Requires-Dist: coverage>=7; extra == "dev"
Requires-Dist: flake8>=5; extra == "dev"
Requires-Dist: tox>=4; extra == "dev"
Requires-Dist: coverage>=7; extra == "dev"
Requires-Dist: black==23.3.0; extra == "dev"
Requires-Dist: flake8==6.0.0; extra == "dev"
Requires-Dist: isort==5.11.4; extra == "dev"
Requires-Dist: pydocstyle[toml]==6.2.3; extra == "dev"
